dgPre/Yuepre.py
dgPre/__init__.py
dgPre-0.1.5.dist-info/METADATA
dgPre-0.1.5.dist-info/WHEEL
dgPre-0.1.5.dist-info/entry_points.txt
dgPre-0.1.5.dist-info/top_level.txt
dgPre-0.1.5.dist-info/zip-safe
dgPre-0.1.5.dist-info/RECORD
